dhvagna_npi/__init__.py
dhvagna_npi/cli.py
dhvagna_npi/config.py
dhvagna_npi/core.py
dhvagna_npi/history.py
dhvagna_npi/ui.py
dhvagna_npi/utils.py
dhvagna_npi-0.1.3.dist-info/licenses/LICENSE
dhvagna_npi-0.1.3.dist-info/METADATA
dhvagna_npi-0.1.3.dist-info/WHEEL
dhvagna_npi-0.1.3.dist-info/entry_points.txt
dhvagna_npi-0.1.3.dist-info/top_level.txt
dhvagna_npi-0.1.3.dist-info/RECORD
