Metadata-Version: 2.4
Name: dhvagna-npi
Version: 0.1.3
Summary: Advanced voice transcription tool with multi-language support
Home-page: https://github.com/gnanesh-16/dhvagna-npi
Author: Gnanesh Balusa
Author-email: Gnanesh Balusa <gnaneshbalusa016g@gmail.com>
License-Expression: MIT
Project-URL: Homepage, https://github.com/gnanesh-16/dhvagna-npi
Project-URL: Bug Tracker, https://github.com/gnanesh-16/dhvagna-npi/issues
Keywords: speech,recognition,transcription,voice,audio
Classifier: Programming Language :: Python :: 3
Classifier: Programming Language :: Python :: 3.7
Classifier: Programming Language :: Python :: 3.8
Classifier: Programming Language :: Python :: 3.9
Classifier: Programming Language :: Python :: 3.10
Classifier: Operating System :: OS Independent
Classifier: Topic :: Multimedia :: Sound/Audio :: Speech
Classifier: Topic :: Text Processing
Requires-Python: >=3.7
License-File: LICENSE
Requires-Dist: SpeechRecognition>=3.8.0
Requires-Dist: keyboard>=0.13.5
Requires-Dist: rich>=10.0.0
Requires-Dist: pyaudio
Requires-Dist: pipwin
Provides-Extra: dev
Requires-Dist: pytest>=7.0.0; extra == "dev"
Requires-Dist: pytest-cov>=3.0.0; extra == "dev"
Requires-Dist: black>=22.0.0; extra == "dev"
Requires-Dist: isort>=5.10.0; extra == "dev"
Requires-Dist: mypy>=0.950; extra == "dev"
Requires-Dist: build>=0.8.0; extra == "dev"
Requires-Dist: twine>=4.0.0; extra == "dev"
Requires-Dist: pre-commit>=2.20.0; extra == "dev"
Dynamic: author
Dynamic: home-page
Dynamic: license-file
Dynamic: provides-extra
Dynamic: requires-python
